[
	{
		"id": "1768105129856-efe1b734329648",
		"uploadedAt": "2026-01-11T04:18:49.856Z",
		"description": "He-TW的头像",
		"images": [
			"/images/pictures/dcb425add78ee04e.jpg"
		]
	},
	{
		"id": "1768105180803-9757b341a65fa8",
		"uploadedAt": "2026-01-11T04:19:40.803Z",
		"description": "红莲Scarlet",
		"images": [
			"/images/pictures/f928e9cf80981a7d.webp"
		]
	},
	{
		"id": "1768105351581-6cb73d4201011",
		"uploadedAt": "2026-01-11T04:22:31.581Z",
		"description": "遐蝶",
		"images": [
			"/images/pictures/dcca13f3c6bc25f9.webp"
		]
	}
]